{
    "parent": "minecraft:recipes/root",
    "rewards": {
      "recipes": [
        "melonslabs:lightning_rod"
      ]
    },
    "criteria": {
      "has_collector": {
        "trigger": "minecraft:inventory_changed",
        "conditions": {
          "items": [
            {
              "item": "melonslabs:lightning_collector"
            }
          ]
        }
      },
      "has_the_recipe": {
        "trigger": "minecraft:recipe_unlocked",
        "conditions": {
          "recipe": "melonslabs:lightning_rod"
        }
      }
    },
    "requirements": [
      [
        "has_collector",
        "has_the_recipe"
      ]
    ]
  }